{"headRefOid":"21ed7d951c741391645de0b2d2140f283725b964","mergeStateStatus":"BLOCKED","mergeable":"MERGEABLE","number":10,"state":"OPEN","statusCheckRollup":[{"__typename":"CheckRun","completedAt":"2026-06-03T02:38:03Z","conclusion":"SKIPPED","detailsUrl":"https://github.com/tonyrowles/patent-cite-tool/actions/runs/26860337715/job/79212314804","name":"verifier-frozen-preflight","startedAt":"2026-06-03T02:38:03Z","status":"COMPLETED","workflowName":"V40 pdfjs Frame-Shift Pre-Flight"},{"__typename":"CheckRun","completedAt":"2026-06-03T02:39:18Z","conclusion":"SUCCESS","detailsUrl":"https://github.com/tonyrowles/patent-cite-tool/actions/runs/26860337712/job/79212314523","name":"ci","startedAt":"2026-06-03T02:38:05Z","status":"COMPLETED","workflowName":"CI"},{"__typename":"CheckRun","completedAt":"2026-06-03T02:39:31Z","conclusion":"SUCCESS","detailsUrl":"https://github.com/tonyrowles/patent-cite-tool/actions/runs/26860337066/job/79212312792","name":"ci","startedAt":"2026-06-03T02:38:04Z","status":"COMPLETED","workflowName":"CI"}]}
